{"p": 0.144, "barbin": 0, "score": 0.000222309989854051, "zyx": [24, 30, 47], "words": [{"color": "#949fe3", "text": "application", "initloc": {"y": 0, "x": 0}, "size": 20}, {"color": "#949fe3", "text": "your", "initloc": {"y": 0, "x": 0}, "size": 20}, {"color": "#949fe3", "text": "want", "initloc": {"y": 0, "x": 0}, "size": 20}, {"color": "#949fe3", "text": "can", "initloc": {"y": 0, "x": 0}, "size": 20}, {"color": "#949fe3", "text": "allows", "initloc": {"y": 0, "x": 0}, "size": 20}, {"color": "#949fe3", "text": "you", "initloc": {"y": 0, "x": 0}, "size": 20}, {"color": "#949fe3", "text": "need", "initloc": {"y": 0, "x": 0}, "size": 20}, {"color": "#949fe3", "text": "ads", "initloc": {"y": 0, "x": 0}, "size": 20}, {"color": "#949fe3", "text": "whatever", "initloc": {"y": 0, "x": 0}, "size": 20}, {"color": "#949fe3", "text": "corporate", "initloc": {"y": 0, "x": 0}, "size": 20}, {"color": "#949fe3", "text": "like", "initloc": {"y": 0, "x": 0}, "size": 20}, {"color": "#949fe3", "text": "wrap", "initloc": {"y": 0, "x": 0}, "size": 20}, {"color": "#949fe3", "text": "include", "initloc": {"y": 0, "x": 0}, "size": 20}, {"color": "#949fe3", "text": "box", "initloc": {"y": 0, "x": 0}, "size": 20}, {"color": "#949fe3", "text": "if", "initloc": {"y": 0, "x": 0}, "size": 20}, {"color": "#949fe3", "text": "so", "initloc": {"y": 0, "x": 0}, "size": 20}, {"color": "#949fe3", "text": "everytime", "initloc": {"y": 0, "x": 0}, "size": 20}, {"color": "#949fe3", "text": "customer", "initloc": {"y": 0, "x": 0}, "size": 20}, {"color": "#949fe3", "text": "cannot", "initloc": {"y": 0, "x": 0}, "size": 20}, {"color": "#949fe3", "text": "custom", "initloc": {"y": 0, "x": 0}, "size": 20}], "cluster": 0.0, "rgb": "#949fe3"}