{"p": 0.38, "barbin": 0, "score": 0.0001622732973682085, "zyx": [17, 37, 49], "words": [{"color": "#FAA236", "text": "it", "initloc": {"y": 0, "x": 0}, "size": 20}, {"color": "#FAA236", "text": "ones", "initloc": {"y": 0, "x": 0}, "size": 20}, {"color": "#FAA236", "text": "the", "initloc": {"y": 0, "x": 0}, "size": 20}, {"color": "#FAA236", "text": "which", "initloc": {"y": 0, "x": 0}, "size": 20}, {"color": "#FAA236", "text": "these", "initloc": {"y": 0, "x": 0}, "size": 20}, {"color": "#FAA236", "text": "being", "initloc": {"y": 0, "x": 0}, "size": 20}, {"color": "#FAA236", "text": "either", "initloc": {"y": 0, "x": 0}, "size": 20}, {"color": "#FAA236", "text": "and", "initloc": {"y": 0, "x": 0}, "size": 20}, {"color": "#FAA236", "text": "completely", "initloc": {"y": 0, "x": 0}, "size": 20}, {"color": "#FAA236", "text": "but", "initloc": {"y": 0, "x": 0}, "size": 20}, {"color": "#FAA236", "text": "that", "initloc": {"y": 0, "x": 0}, "size": 20}, {"color": "#FAA236", "text": "they", "initloc": {"y": 0, "x": 0}, "size": 20}, {"color": "#FAA236", "text": "are", "initloc": {"y": 0, "x": 0}, "size": 20}, {"color": "#FAA236", "text": "were", "initloc": {"y": 0, "x": 0}, "size": 20}, {"color": "#FAA236", "text": "actually", "initloc": {"y": 0, "x": 0}, "size": 20}, {"color": "#FAA236", "text": "those", "initloc": {"y": 0, "x": 0}, "size": 20}, {"color": "#FAA236", "text": "totally", "initloc": {"y": 0, "x": 0}, "size": 20}, {"color": "#FAA236", "text": "just", "initloc": {"y": 0, "x": 0}, "size": 20}, {"color": "#FAA236", "text": "be", "initloc": {"y": 0, "x": 0}, "size": 20}, {"color": "#FAA236", "text": "other", "initloc": {"y": 0, "x": 0}, "size": 20}], "cluster": 2.0, "rgb": "#FAA236"}