{"barbin": 0, "zyx": [11, 49, 78], "score_en": 0.0, "score_zh": 0.0860227407608048, "words_pos": [{"color": "#ad00c4", "text": "was", "initloc": {"y": 0, "x": 0}, "size": 20}, {"color": "#ad00c4", "text": "represented", "initloc": {"y": 0, "x": 0}, "size": 20}, {"color": "#ad00c4", "text": "seventeen", "initloc": {"y": 0, "x": 0}, "size": 20}, {"color": "#ad00c4", "text": "were", "initloc": {"y": 0, "x": 0}, "size": 20}, {"color": "#ad00c4", "text": "survived", "initloc": {"y": 0, "x": 0}, "size": 20}, {"color": "#ad00c4", "text": "previously", "initloc": {"y": 0, "x": 0}, "size": 20}, {"color": "#ad00c4", "text": "had", "initloc": {"y": 0, "x": 0}, "size": 20}, {"color": "#ad00c4", "text": "tenure", "initloc": {"y": 0, "x": 0}, "size": 20}, {"color": "#ad00c4", "text": "years", "initloc": {"y": 0, "x": 0}, "size": 20}, {"color": "#ad00c4", "text": "eleven", "initloc": {"y": 0, "x": 0}, "size": 20}, {"color": "#ad00c4", "text": "nineteen", "initloc": {"y": 0, "x": 0}, "size": 20}, {"color": "#ad00c4", "text": "thirty", "initloc": {"y": 0, "x": 0}, "size": 20}, {"color": "#ad00c4", "text": "fifteen", "initloc": {"y": 0, "x": 0}, "size": 20}, {"color": "#ad00c4", "text": "of", "initloc": {"y": 0, "x": 0}, "size": 20}, {"color": "#ad00c4", "text": "by", "initloc": {"y": 0, "x": 0}, "size": 20}, {"color": "#ad00c4", "text": "seven", "initloc": {"y": 0, "x": 0}, "size": 20}, {"color": "#ad00c4", "text": "and", "initloc": {"y": 0, "x": 0}, "size": 20}, {"color": "#ad00c4", "text": "since", "initloc": {"y": 0, "x": 0}, "size": 20}, {"color": "#ad00c4", "text": "eight", "initloc": {"y": 0, "x": 0}, "size": 20}, {"color": "#ad00c4", "text": "later", "initloc": {"y": 0, "x": 0}, "size": 20}], "words_neg": [{"color": "#06910a", "text": "you", "initloc": {"y": 0, "x": 0}, "size": 20}, {"color": "#06910a", "text": "want", "initloc": {"y": 0, "x": 0}, "size": 20}, {"color": "#06910a", "text": "your", "initloc": {"y": 0, "x": 0}, "size": 20}, {"color": "#06910a", "text": "ask", "initloc": {"y": 0, "x": 0}, "size": 20}, {"color": "#06910a", "text": "everyone", "initloc": {"y": 0, "x": 0}, "size": 20}, {"color": "#06910a", "text": "know", "initloc": {"y": 0, "x": 0}, "size": 20}, {"color": "#06910a", "text": "welcome", "initloc": {"y": 0, "x": 0}, "size": 20}, {"color": "#06910a", "text": "thank", "initloc": {"y": 0, "x": 0}, "size": 20}, {"color": "#06910a", "text": "me", "initloc": {"y": 0, "x": 0}, "size": 20}, {"color": "#06910a", "text": "everybody", "initloc": {"y": 0, "x": 0}, "size": 20}, {"color": "#06910a", "text": "somebody", "initloc": {"y": 0, "x": 0}, "size": 20}, {"color": "#06910a", "text": "something", "initloc": {"y": 0, "x": 0}, "size": 20}, {"color": "#06910a", "text": "get", "initloc": {"y": 0, "x": 0}, "size": 20}, {"color": "#06910a", "text": "thing", "initloc": {"y": 0, "x": 0}, "size": 20}, {"color": "#06910a", "text": "stuff", "initloc": {"y": 0, "x": 0}, "size": 20}, {"color": "#06910a", "text": "things", "initloc": {"y": 0, "x": 0}, "size": 20}, {"color": "#06910a", "text": "whatever", "initloc": {"y": 0, "x": 0}, "size": 20}, {"color": "#06910a", "text": "anybody", "initloc": {"y": 0, "x": 0}, "size": 20}, {"color": "#06910a", "text": "anyway", "initloc": {"y": 0, "x": 0}, "size": 20}, {"color": "#06910a", "text": "go", "initloc": {"y": 0, "x": 0}, "size": 20}], "ptsi": -0.16066011697989097, "rgb": "#ceb5d7"}