{"barbin": 0, "zyx": [10, 49, 24], "score_en": 0.00019036672464138254, "score_zh": 0.00046374364155473866, "words_pos": [{"color": "#06910a", "text": "furniture", "initloc": {"y": 0, "x": 0}, "size": 20}, {"color": "#06910a", "text": "are", "initloc": {"y": 0, "x": 0}, "size": 20}, {"color": "#06910a", "text": "piles", "initloc": {"y": 0, "x": 0}, "size": 20}, {"color": "#06910a", "text": "were", "initloc": {"y": 0, "x": 0}, "size": 20}, {"color": "#06910a", "text": "posters", "initloc": {"y": 0, "x": 0}, "size": 20}, {"color": "#06910a", "text": "baggy", "initloc": {"y": 0, "x": 0}, "size": 20}, {"color": "#06910a", "text": "sluttiest", "initloc": {"y": 0, "x": 0}, "size": 20}, {"color": "#06910a", "text": "cloth", "initloc": {"y": 0, "x": 0}, "size": 20}, {"color": "#06910a", "text": "jewelry", "initloc": {"y": 0, "x": 0}, "size": 20}, {"color": "#06910a", "text": "producer", "initloc": {"y": 0, "x": 0}, "size": 20}, {"color": "#06910a", "text": "bookcases", "initloc": {"y": 0, "x": 0}, "size": 20}, {"color": "#06910a", "text": "rackets", "initloc": {"y": 0, "x": 0}, "size": 20}, {"color": "#06910a", "text": "these", "initloc": {"y": 0, "x": 0}, "size": 20}, {"color": "#06910a", "text": "notoriously", "initloc": {"y": 0, "x": 0}, "size": 20}, {"color": "#06910a", "text": "nuts", "initloc": {"y": 0, "x": 0}, "size": 20}, {"color": "#06910a", "text": "napkins", "initloc": {"y": 0, "x": 0}, "size": 20}, {"color": "#06910a", "text": "branches", "initloc": {"y": 0, "x": 0}, "size": 20}, {"color": "#06910a", "text": "particularly", "initloc": {"y": 0, "x": 0}, "size": 20}, {"color": "#06910a", "text": "neat", "initloc": {"y": 0, "x": 0}, "size": 20}, {"color": "#06910a", "text": "camps", "initloc": {"y": 0, "x": 0}, "size": 20}], "words_neg": [{"color": "#ad00c4", "text": "to", "initloc": {"y": 0, "x": 0}, "size": 20}, {"color": "#ad00c4", "text": "a", "initloc": {"y": 0, "x": 0}, "size": 20}, {"color": "#ad00c4", "text": "welcome", "initloc": {"y": 0, "x": 0}, "size": 20}, {"color": "#ad00c4", "text": "chance", "initloc": {"y": 0, "x": 0}, "size": 20}, {"color": "#ad00c4", "text": "another", "initloc": {"y": 0, "x": 0}, "size": 20}, {"color": "#ad00c4", "text": "visit", "initloc": {"y": 0, "x": 0}, "size": 20}, {"color": "#ad00c4", "text": "weeks", "initloc": {"y": 0, "x": 0}, "size": 20}, {"color": "#ad00c4", "text": "bye", "initloc": {"y": 0, "x": 0}, "size": 20}, {"color": "#ad00c4", "text": "back", "initloc": {"y": 0, "x": 0}, "size": 20}, {"color": "#ad00c4", "text": "ask", "initloc": {"y": 0, "x": 0}, "size": 20}, {"color": "#ad00c4", "text": "me", "initloc": {"y": 0, "x": 0}, "size": 20}, {"color": "#ad00c4", "text": "yesterday", "initloc": {"y": 0, "x": 0}, "size": 20}, {"color": "#ad00c4", "text": "minutes", "initloc": {"y": 0, "x": 0}, "size": 20}, {"color": "#ad00c4", "text": "month", "initloc": {"y": 0, "x": 0}, "size": 20}, {"color": "#ad00c4", "text": "asked", "initloc": {"y": 0, "x": 0}, "size": 20}, {"color": "#ad00c4", "text": "sign", "initloc": {"y": 0, "x": 0}, "size": 20}, {"color": "#ad00c4", "text": "hour", "initloc": {"y": 0, "x": 0}, "size": 20}, {"color": "#ad00c4", "text": "next", "initloc": {"y": 0, "x": 0}, "size": 20}, {"color": "#ad00c4", "text": "first", "initloc": {"y": 0, "x": 0}, "size": 20}, {"color": "#ad00c4", "text": "counseled", "initloc": {"y": 0, "x": 0}, "size": 20}], "ptsi": 0.09370693735436676, "rgb": "#daefd4"}