{"barbin": 0, "zyx": [10, 20, 43], "score_en": 0.0004153387947590773, "score_zh": 0.0002502088683595388, "words_pos": [{"color": "#06910a", "text": "know", "initloc": {"y": 0, "x": 0}, "size": 20}, {"color": "#06910a", "text": "knows", "initloc": {"y": 0, "x": 0}, "size": 20}, {"color": "#06910a", "text": "understand", "initloc": {"y": 0, "x": 0}, "size": 20}, {"color": "#06910a", "text": "quite", "initloc": {"y": 0, "x": 0}, "size": 20}, {"color": "#06910a", "text": "realize", "initloc": {"y": 0, "x": 0}, "size": 20}, {"color": "#06910a", "text": "thinks", "initloc": {"y": 0, "x": 0}, "size": 20}, {"color": "#06910a", "text": "doing", "initloc": {"y": 0, "x": 0}, "size": 20}, {"color": "#06910a", "text": "believe", "initloc": {"y": 0, "x": 0}, "size": 20}, {"color": "#06910a", "text": "worry", "initloc": {"y": 0, "x": 0}, "size": 20}, {"color": "#06910a", "text": "appreciate", "initloc": {"y": 0, "x": 0}, "size": 20}, {"color": "#06910a", "text": "seem", "initloc": {"y": 0, "x": 0}, "size": 20}, {"color": "#06910a", "text": "frankly", "initloc": {"y": 0, "x": 0}, "size": 20}, {"color": "#06910a", "text": "you", "initloc": {"y": 0, "x": 0}, "size": 20}, {"color": "#06910a", "text": "think", "initloc": {"y": 0, "x": 0}, "size": 20}, {"color": "#06910a", "text": "liar", "initloc": {"y": 0, "x": 0}, "size": 20}, {"color": "#06910a", "text": "terribly", "initloc": {"y": 0, "x": 0}, "size": 20}, {"color": "#06910a", "text": "have", "initloc": {"y": 0, "x": 0}, "size": 20}, {"color": "#06910a", "text": "really", "initloc": {"y": 0, "x": 0}, "size": 20}, {"color": "#06910a", "text": "learn", "initloc": {"y": 0, "x": 0}, "size": 20}, {"color": "#06910a", "text": "insanely", "initloc": {"y": 0, "x": 0}, "size": 20}], "words_neg": [{"color": "#ad00c4", "text": "the", "initloc": {"y": 0, "x": 0}, "size": 20}, {"color": "#ad00c4", "text": "of", "initloc": {"y": 0, "x": 0}, "size": 20}, {"color": "#ad00c4", "text": "after", "initloc": {"y": 0, "x": 0}, "size": 20}, {"color": "#ad00c4", "text": "half", "initloc": {"y": 0, "x": 0}, "size": 20}, {"color": "#ad00c4", "text": "then", "initloc": {"y": 0, "x": 0}, "size": 20}, {"color": "#ad00c4", "text": "onto", "initloc": {"y": 0, "x": 0}, "size": 20}, {"color": "#ad00c4", "text": "into", "initloc": {"y": 0, "x": 0}, "size": 20}, {"color": "#ad00c4", "text": "at", "initloc": {"y": 0, "x": 0}, "size": 20}, {"color": "#ad00c4", "text": "later", "initloc": {"y": 0, "x": 0}, "size": 20}, {"color": "#ad00c4", "text": "before", "initloc": {"y": 0, "x": 0}, "size": 20}, {"color": "#ad00c4", "text": "and", "initloc": {"y": 0, "x": 0}, "size": 20}, {"color": "#ad00c4", "text": "two", "initloc": {"y": 0, "x": 0}, "size": 20}, {"color": "#ad00c4", "text": "end", "initloc": {"y": 0, "x": 0}, "size": 20}, {"color": "#ad00c4", "text": "between", "initloc": {"y": 0, "x": 0}, "size": 20}, {"color": "#ad00c4", "text": "over", "initloc": {"y": 0, "x": 0}, "size": 20}, {"color": "#ad00c4", "text": "afterwards", "initloc": {"y": 0, "x": 0}, "size": 20}, {"color": "#ad00c4", "text": "second", "initloc": {"y": 0, "x": 0}, "size": 20}, {"color": "#ad00c4", "text": "for", "initloc": {"y": 0, "x": 0}, "size": 20}, {"color": "#ad00c4", "text": "was", "initloc": {"y": 0, "x": 0}, "size": 20}, {"color": "#ad00c4", "text": "ninety", "initloc": {"y": 0, "x": 0}, "size": 20}], "ptsi": 0.1329529730813011, "rgb": "#c6e7c0"}