{"barbin": 0, "zyx": [4, 45, 39], "score_en": 0.0001497569261817411, "score_zh": 0.0, "words_pos": [{"color": "#ad00c4", "text": "of", "initloc": {"y": 0, "x": 0}, "size": 20}, {"color": "#ad00c4", "text": "between", "initloc": {"y": 0, "x": 0}, "size": 20}, {"color": "#ad00c4", "text": "among", "initloc": {"y": 0, "x": 0}, "size": 20}, {"color": "#ad00c4", "text": "mutually", "initloc": {"y": 0, "x": 0}, "size": 20}, {"color": "#ad00c4", "text": "several", "initloc": {"y": 0, "x": 0}, "size": 20}, {"color": "#ad00c4", "text": "and", "initloc": {"y": 0, "x": 0}, "size": 20}, {"color": "#ad00c4", "text": "remains", "initloc": {"y": 0, "x": 0}, "size": 20}, {"color": "#ad00c4", "text": "represents", "initloc": {"y": 0, "x": 0}, "size": 20}, {"color": "#ad00c4", "text": "its", "initloc": {"y": 0, "x": 0}, "size": 20}, {"color": "#ad00c4", "text": "other", "initloc": {"y": 0, "x": 0}, "size": 20}, {"color": "#ad00c4", "text": "extent", "initloc": {"y": 0, "x": 0}, "size": 20}, {"color": "#ad00c4", "text": "the", "initloc": {"y": 0, "x": 0}, "size": 20}, {"color": "#ad00c4", "text": "universes", "initloc": {"y": 0, "x": 0}, "size": 20}, {"color": "#ad00c4", "text": "along", "initloc": {"y": 0, "x": 0}, "size": 20}, {"color": "#ad00c4", "text": "whose", "initloc": {"y": 0, "x": 0}, "size": 20}, {"color": "#ad00c4", "text": "their", "initloc": {"y": 0, "x": 0}, "size": 20}, {"color": "#ad00c4", "text": "inhabit", "initloc": {"y": 0, "x": 0}, "size": 20}, {"color": "#ad00c4", "text": "previously", "initloc": {"y": 0, "x": 0}, "size": 20}, {"color": "#ad00c4", "text": "branches", "initloc": {"y": 0, "x": 0}, "size": 20}, {"color": "#ad00c4", "text": "include", "initloc": {"y": 0, "x": 0}, "size": 20}], "words_neg": [{"color": "#06910a", "text": "gonna", "initloc": {"y": 0, "x": 0}, "size": 20}, {"color": "#06910a", "text": "anymore", "initloc": {"y": 0, "x": 0}, "size": 20}, {"color": "#06910a", "text": "alright", "initloc": {"y": 0, "x": 0}, "size": 20}, {"color": "#06910a", "text": "really", "initloc": {"y": 0, "x": 0}, "size": 20}, {"color": "#06910a", "text": "um", "initloc": {"y": 0, "x": 0}, "size": 20}, {"color": "#06910a", "text": "nice", "initloc": {"y": 0, "x": 0}, "size": 20}, {"color": "#06910a", "text": "going", "initloc": {"y": 0, "x": 0}, "size": 20}, {"color": "#06910a", "text": "yeah", "initloc": {"y": 0, "x": 0}, "size": 20}, {"color": "#06910a", "text": "doing", "initloc": {"y": 0, "x": 0}, "size": 20}, {"color": "#06910a", "text": "excuse", "initloc": {"y": 0, "x": 0}, "size": 20}, {"color": "#06910a", "text": "go", "initloc": {"y": 0, "x": 0}, "size": 20}, {"color": "#06910a", "text": "everybody", "initloc": {"y": 0, "x": 0}, "size": 20}, {"color": "#06910a", "text": "t", "initloc": {"y": 0, "x": 0}, "size": 20}, {"color": "#06910a", "text": "you", "initloc": {"y": 0, "x": 0}, "size": 20}, {"color": "#06910a", "text": "shit", "initloc": {"y": 0, "x": 0}, "size": 20}, {"color": "#06910a", "text": "goddamn", "initloc": {"y": 0, "x": 0}, "size": 20}, {"color": "#06910a", "text": "i", "initloc": {"y": 0, "x": 0}, "size": 20}, {"color": "#06910a", "text": "darn", "initloc": {"y": 0, "x": 0}, "size": 20}, {"color": "#06910a", "text": "me", "initloc": {"y": 0, "x": 0}, "size": 20}, {"color": "#06910a", "text": "ready", "initloc": {"y": 0, "x": 0}, "size": 20}], "ptsi": -0.10019944199899591, "rgb": "#e6d3e7"}