{"barbin": 0, "zyx": [15, 46, 80], "score_en": 0.0, "score_zh": 0.0008372502994575627, "words_pos": [{"color": "#06910a", "text": "we", "initloc": {"y": 0, "x": 0}, "size": 20}, {"color": "#06910a", "text": "think", "initloc": {"y": 0, "x": 0}, "size": 20}, {"color": "#06910a", "text": "apologize", "initloc": {"y": 0, "x": 0}, "size": 20}, {"color": "#06910a", "text": "myself", "initloc": {"y": 0, "x": 0}, "size": 20}, {"color": "#06910a", "text": "i", "initloc": {"y": 0, "x": 0}, "size": 20}, {"color": "#06910a", "text": "anyway", "initloc": {"y": 0, "x": 0}, "size": 20}, {"color": "#06910a", "text": "everyone", "initloc": {"y": 0, "x": 0}, "size": 20}, {"color": "#06910a", "text": "yeah", "initloc": {"y": 0, "x": 0}, "size": 20}, {"color": "#06910a", "text": "say", "initloc": {"y": 0, "x": 0}, "size": 20}, {"color": "#06910a", "text": "remember", "initloc": {"y": 0, "x": 0}, "size": 20}, {"color": "#06910a", "text": "my", "initloc": {"y": 0, "x": 0}, "size": 20}, {"color": "#06910a", "text": "right", "initloc": {"y": 0, "x": 0}, "size": 20}, {"color": "#06910a", "text": "you", "initloc": {"y": 0, "x": 0}, "size": 20}, {"color": "#06910a", "text": "frankly", "initloc": {"y": 0, "x": 0}, "size": 20}, {"color": "#06910a", "text": "your", "initloc": {"y": 0, "x": 0}, "size": 20}, {"color": "#06910a", "text": "maybe", "initloc": {"y": 0, "x": 0}, "size": 20}, {"color": "#06910a", "text": "want", "initloc": {"y": 0, "x": 0}, "size": 20}, {"color": "#06910a", "text": "appreciate", "initloc": {"y": 0, "x": 0}, "size": 20}, {"color": "#06910a", "text": "ourselves", "initloc": {"y": 0, "x": 0}, "size": 20}, {"color": "#06910a", "text": "yesterday", "initloc": {"y": 0, "x": 0}, "size": 20}], "words_neg": [{"color": "#ad00c4", "text": "jt", "initloc": {"y": 0, "x": 0}, "size": 20}, {"color": "#ad00c4", "text": "partner", "initloc": {"y": 0, "x": 0}, "size": 20}, {"color": "#ad00c4", "text": "leroy", "initloc": {"y": 0, "x": 0}, "size": 20}, {"color": "#ad00c4", "text": "with", "initloc": {"y": 0, "x": 0}, "size": 20}, {"color": "#ad00c4", "text": "and", "initloc": {"y": 0, "x": 0}, "size": 20}, {"color": "#ad00c4", "text": "by", "initloc": {"y": 0, "x": 0}, "size": 20}, {"color": "#ad00c4", "text": "companion", "initloc": {"y": 0, "x": 0}, "size": 20}, {"color": "#ad00c4", "text": "deal", "initloc": {"y": 0, "x": 0}, "size": 20}, {"color": "#ad00c4", "text": "s", "initloc": {"y": 0, "x": 0}, "size": 20}, {"color": "#ad00c4", "text": "relationship", "initloc": {"y": 0, "x": 0}, "size": 20}, {"color": "#ad00c4", "text": "ad", "initloc": {"y": 0, "x": 0}, "size": 20}, {"color": "#ad00c4", "text": "smart", "initloc": {"y": 0, "x": 0}, "size": 20}, {"color": "#ad00c4", "text": "in", "initloc": {"y": 0, "x": 0}, "size": 20}, {"color": "#ad00c4", "text": "rudy", "initloc": {"y": 0, "x": 0}, "size": 20}, {"color": "#ad00c4", "text": "beautiful", "initloc": {"y": 0, "x": 0}, "size": 20}, {"color": "#ad00c4", "text": "samantha", "initloc": {"y": 0, "x": 0}, "size": 20}, {"color": "#ad00c4", "text": "wise", "initloc": {"y": 0, "x": 0}, "size": 20}, {"color": "#ad00c4", "text": "story", "initloc": {"y": 0, "x": 0}, "size": 20}, {"color": "#ad00c4", "text": "con", "initloc": {"y": 0, "x": 0}, "size": 20}, {"color": "#ad00c4", "text": "beauty", "initloc": {"y": 0, "x": 0}, "size": 20}], "ptsi": 0.07269895103067331, "rgb": "#e0f0db"}