{"barbin": 0, "zyx": [5, 31, 30], "score_en": 0.0003065617985165338, "score_zh": 0.0002090794614537914, "words_pos": [{"color": "#ad00c4", "text": "before", "initloc": {"y": 0, "x": 0}, "size": 20}, {"color": "#ad00c4", "text": "near", "initloc": {"y": 0, "x": 0}, "size": 20}, {"color": "#ad00c4", "text": "drove", "initloc": {"y": 0, "x": 0}, "size": 20}, {"color": "#ad00c4", "text": "at", "initloc": {"y": 0, "x": 0}, "size": 20}, {"color": "#ad00c4", "text": "after", "initloc": {"y": 0, "x": 0}, "size": 20}, {"color": "#ad00c4", "text": "until", "initloc": {"y": 0, "x": 0}, "size": 20}, {"color": "#ad00c4", "text": "occurred", "initloc": {"y": 0, "x": 0}, "size": 20}, {"color": "#ad00c4", "text": "later", "initloc": {"y": 0, "x": 0}, "size": 20}, {"color": "#ad00c4", "text": "fled", "initloc": {"y": 0, "x": 0}, "size": 20}, {"color": "#ad00c4", "text": "of", "initloc": {"y": 0, "x": 0}, "size": 20}, {"color": "#ad00c4", "text": "starting", "initloc": {"y": 0, "x": 0}, "size": 20}, {"color": "#ad00c4", "text": "the", "initloc": {"y": 0, "x": 0}, "size": 20}, {"color": "#ad00c4", "text": "took", "initloc": {"y": 0, "x": 0}, "size": 20}, {"color": "#ad00c4", "text": "begins", "initloc": {"y": 0, "x": 0}, "size": 20}, {"color": "#ad00c4", "text": "afterwards", "initloc": {"y": 0, "x": 0}, "size": 20}, {"color": "#ad00c4", "text": "prior", "initloc": {"y": 0, "x": 0}, "size": 20}, {"color": "#ad00c4", "text": "between", "initloc": {"y": 0, "x": 0}, "size": 20}, {"color": "#ad00c4", "text": "ended", "initloc": {"y": 0, "x": 0}, "size": 20}, {"color": "#ad00c4", "text": "reaches", "initloc": {"y": 0, "x": 0}, "size": 20}, {"color": "#ad00c4", "text": "end", "initloc": {"y": 0, "x": 0}, "size": 20}], "words_neg": [{"color": "#06910a", "text": "good", "initloc": {"y": 0, "x": 0}, "size": 20}, {"color": "#06910a", "text": "honesty", "initloc": {"y": 0, "x": 0}, "size": 20}, {"color": "#06910a", "text": "cute", "initloc": {"y": 0, "x": 0}, "size": 20}, {"color": "#06910a", "text": "terribly", "initloc": {"y": 0, "x": 0}, "size": 20}, {"color": "#06910a", "text": "easy", "initloc": {"y": 0, "x": 0}, "size": 20}, {"color": "#06910a", "text": "eyelashes", "initloc": {"y": 0, "x": 0}, "size": 20}, {"color": "#06910a", "text": "stuff", "initloc": {"y": 0, "x": 0}, "size": 20}, {"color": "#06910a", "text": "pretty", "initloc": {"y": 0, "x": 0}, "size": 20}, {"color": "#06910a", "text": "eyeshadow", "initloc": {"y": 0, "x": 0}, "size": 20}, {"color": "#06910a", "text": "really", "initloc": {"y": 0, "x": 0}, "size": 20}, {"color": "#06910a", "text": "unexceptional", "initloc": {"y": 0, "x": 0}, "size": 20}, {"color": "#06910a", "text": "leggy", "initloc": {"y": 0, "x": 0}, "size": 20}, {"color": "#06910a", "text": "chore", "initloc": {"y": 0, "x": 0}, "size": 20}, {"color": "#06910a", "text": "appreciate", "initloc": {"y": 0, "x": 0}, "size": 20}, {"color": "#06910a", "text": "disgusting", "initloc": {"y": 0, "x": 0}, "size": 20}, {"color": "#06910a", "text": "done", "initloc": {"y": 0, "x": 0}, "size": 20}, {"color": "#06910a", "text": "tools", "initloc": {"y": 0, "x": 0}, "size": 20}, {"color": "#06910a", "text": "proud", "initloc": {"y": 0, "x": 0}, "size": 20}, {"color": "#06910a", "text": "very", "initloc": {"y": 0, "x": 0}, "size": 20}, {"color": "#06910a", "text": "quite", "initloc": {"y": 0, "x": 0}, "size": 20}], "ptsi": -0.06414445840520556, "rgb": "#eadfec"}