{"barbin": 0, "zyx": [21, 42, 27], "score_en": 0.0006516445185389215, "score_zh": 0.12953814047742912, "words_pos": [{"color": "#06910a", "text": "thinks", "initloc": {"y": 0, "x": 0}, "size": 20}, {"color": "#06910a", "text": "realize", "initloc": {"y": 0, "x": 0}, "size": 20}, {"color": "#06910a", "text": "believe", "initloc": {"y": 0, "x": 0}, "size": 20}, {"color": "#06910a", "text": "happier", "initloc": {"y": 0, "x": 0}, "size": 20}, {"color": "#06910a", "text": "everyone", "initloc": {"y": 0, "x": 0}, "size": 20}, {"color": "#06910a", "text": "worry", "initloc": {"y": 0, "x": 0}, "size": 20}, {"color": "#06910a", "text": "felt", "initloc": {"y": 0, "x": 0}, "size": 20}, {"color": "#06910a", "text": "knows", "initloc": {"y": 0, "x": 0}, "size": 20}, {"color": "#06910a", "text": "saying", "initloc": {"y": 0, "x": 0}, "size": 20}, {"color": "#06910a", "text": "interested", "initloc": {"y": 0, "x": 0}, "size": 20}, {"color": "#06910a", "text": "wants", "initloc": {"y": 0, "x": 0}, "size": 20}, {"color": "#06910a", "text": "tells", "initloc": {"y": 0, "x": 0}, "size": 20}, {"color": "#06910a", "text": "told", "initloc": {"y": 0, "x": 0}, "size": 20}, {"color": "#06910a", "text": "feel", "initloc": {"y": 0, "x": 0}, "size": 20}, {"color": "#06910a", "text": "said", "initloc": {"y": 0, "x": 0}, "size": 20}, {"color": "#06910a", "text": "mentally", "initloc": {"y": 0, "x": 0}, "size": 20}, {"color": "#06910a", "text": "knew", "initloc": {"y": 0, "x": 0}, "size": 20}, {"color": "#06910a", "text": "really", "initloc": {"y": 0, "x": 0}, "size": 20}, {"color": "#06910a", "text": "supportive", "initloc": {"y": 0, "x": 0}, "size": 20}, {"color": "#06910a", "text": "telling", "initloc": {"y": 0, "x": 0}, "size": 20}], "words_neg": [{"color": "#ad00c4", "text": "lit", "initloc": {"y": 0, "x": 0}, "size": 20}, {"color": "#ad00c4", "text": "corner", "initloc": {"y": 0, "x": 0}, "size": 20}, {"color": "#ad00c4", "text": "roll", "initloc": {"y": 0, "x": 0}, "size": 20}, {"color": "#ad00c4", "text": "ran", "initloc": {"y": 0, "x": 0}, "size": 20}, {"color": "#ad00c4", "text": "flames", "initloc": {"y": 0, "x": 0}, "size": 20}, {"color": "#ad00c4", "text": "b", "initloc": {"y": 0, "x": 0}, "size": 20}, {"color": "#ad00c4", "text": "in", "initloc": {"y": 0, "x": 0}, "size": 20}, {"color": "#ad00c4", "text": "side", "initloc": {"y": 0, "x": 0}, "size": 20}, {"color": "#ad00c4", "text": "ing", "initloc": {"y": 0, "x": 0}, "size": 20}, {"color": "#ad00c4", "text": "and", "initloc": {"y": 0, "x": 0}, "size": 20}, {"color": "#ad00c4", "text": "flight", "initloc": {"y": 0, "x": 0}, "size": 20}, {"color": "#ad00c4", "text": "blue", "initloc": {"y": 0, "x": 0}, "size": 20}, {"color": "#ad00c4", "text": "meaning", "initloc": {"y": 0, "x": 0}, "size": 20}, {"color": "#ad00c4", "text": "a", "initloc": {"y": 0, "x": 0}, "size": 20}, {"color": "#ad00c4", "text": "readings", "initloc": {"y": 0, "x": 0}, "size": 20}, {"color": "#ad00c4", "text": "fo", "initloc": {"y": 0, "x": 0}, "size": 20}, {"color": "#ad00c4", "text": "jig", "initloc": {"y": 0, "x": 0}, "size": 20}, {"color": "#ad00c4", "text": "walls", "initloc": {"y": 0, "x": 0}, "size": 20}, {"color": "#ad00c4", "text": "bank", "initloc": {"y": 0, "x": 0}, "size": 20}, {"color": "#ad00c4", "text": "the", "initloc": {"y": 0, "x": 0}, "size": 20}], "ptsi": 0.33488752496532587, "rgb": "#429951"}