{"p": 0.065, "barbin": 0, "score": 0.08002445916463641, "zyx": [9, 46, 26], "words": [{"color": "#F2EC14", "text": "sooner", "initloc": {"y": 0, "x": 0}, "size": 20}, {"color": "#F2EC14", "text": "just", "initloc": {"y": 0, "x": 0}, "size": 20}, {"color": "#F2EC14", "text": "before", "initloc": {"y": 0, "x": 0}, "size": 20}, {"color": "#F2EC14", "text": "happier", "initloc": {"y": 0, "x": 0}, "size": 20}, {"color": "#F2EC14", "text": "weeks", "initloc": {"y": 0, "x": 0}, "size": 20}, {"color": "#F2EC14", "text": "seeing", "initloc": {"y": 0, "x": 0}, "size": 20}, {"color": "#F2EC14", "text": "glanced", "initloc": {"y": 0, "x": 0}, "size": 20}, {"color": "#F2EC14", "text": "watching", "initloc": {"y": 0, "x": 0}, "size": 20}, {"color": "#F2EC14", "text": "looked", "initloc": {"y": 0, "x": 0}, "size": 20}, {"color": "#F2EC14", "text": "exams", "initloc": {"y": 0, "x": 0}, "size": 20}, {"color": "#F2EC14", "text": "maybe", "initloc": {"y": 0, "x": 0}, "size": 20}, {"color": "#F2EC14", "text": "too", "initloc": {"y": 0, "x": 0}, "size": 20}, {"color": "#F2EC14", "text": "moment", "initloc": {"y": 0, "x": 0}, "size": 20}, {"color": "#F2EC14", "text": "slowly", "initloc": {"y": 0, "x": 0}, "size": 20}, {"color": "#F2EC14", "text": "feeling", "initloc": {"y": 0, "x": 0}, "size": 20}, {"color": "#F2EC14", "text": "going", "initloc": {"y": 0, "x": 0}, "size": 20}, {"color": "#F2EC14", "text": "days", "initloc": {"y": 0, "x": 0}, "size": 20}, {"color": "#F2EC14", "text": "noticing", "initloc": {"y": 0, "x": 0}, "size": 20}, {"color": "#F2EC14", "text": "anyway", "initloc": {"y": 0, "x": 0}, "size": 20}, {"color": "#F2EC14", "text": "remember", "initloc": {"y": 0, "x": 0}, "size": 20}], "cluster": 3.0, "rgb": "#F2EC14"}