{"p": 0.0, "barbin": 3, "score": 0.187154985701142, "zyx": [20, 32, 47], "words": [{"color": "#F2EC14", "text": "yesterday", "initloc": {"y": 0, "x": 0}, "size": 20}, {"color": "#F2EC14", "text": "falling", "initloc": {"y": 0, "x": 0}, "size": 20}, {"color": "#F2EC14", "text": "dropping", "initloc": {"y": 0, "x": 0}, "size": 20}, {"color": "#F2EC14", "text": "glanced", "initloc": {"y": 0, "x": 0}, "size": 20}, {"color": "#F2EC14", "text": "down", "initloc": {"y": 0, "x": 0}, "size": 20}, {"color": "#F2EC14", "text": "swung", "initloc": {"y": 0, "x": 0}, "size": 20}, {"color": "#F2EC14", "text": "blurted", "initloc": {"y": 0, "x": 0}, "size": 20}, {"color": "#F2EC14", "text": "fell", "initloc": {"y": 0, "x": 0}, "size": 20}, {"color": "#F2EC14", "text": "jumped", "initloc": {"y": 0, "x": 0}, "size": 20}, {"color": "#F2EC14", "text": "morning", "initloc": {"y": 0, "x": 0}, "size": 20}, {"color": "#F2EC14", "text": "minutes", "initloc": {"y": 0, "x": 0}, "size": 20}, {"color": "#F2EC14", "text": "walked", "initloc": {"y": 0, "x": 0}, "size": 20}, {"color": "#F2EC14", "text": "suddenly", "initloc": {"y": 0, "x": 0}, "size": 20}, {"color": "#F2EC14", "text": "stopped", "initloc": {"y": 0, "x": 0}, "size": 20}, {"color": "#F2EC14", "text": "leans", "initloc": {"y": 0, "x": 0}, "size": 20}, {"color": "#F2EC14", "text": "screamed", "initloc": {"y": 0, "x": 0}, "size": 20}, {"color": "#F2EC14", "text": "hours", "initloc": {"y": 0, "x": 0}, "size": 20}, {"color": "#F2EC14", "text": "hour", "initloc": {"y": 0, "x": 0}, "size": 20}, {"color": "#F2EC14", "text": "hike", "initloc": {"y": 0, "x": 0}, "size": 20}, {"color": "#F2EC14", "text": "pulled", "initloc": {"y": 0, "x": 0}, "size": 20}], "cluster": 3.0, "rgb": "#F2EC14"}