{"p": 0.45, "barbin": 0, "score": 0.00014249596012282936, "zyx": [3, 47, 63], "words": [{"color": "#949fe3", "text": "swear", "initloc": {"y": 0, "x": 0}, "size": 20}, {"color": "#949fe3", "text": "ass", "initloc": {"y": 0, "x": 0}, "size": 20}, {"color": "#949fe3", "text": "liar", "initloc": {"y": 0, "x": 0}, "size": 20}, {"color": "#949fe3", "text": "pay", "initloc": {"y": 0, "x": 0}, "size": 20}, {"color": "#949fe3", "text": "honesty", "initloc": {"y": 0, "x": 0}, "size": 20}, {"color": "#949fe3", "text": "goddamn", "initloc": {"y": 0, "x": 0}, "size": 20}, {"color": "#949fe3", "text": "grumpy", "initloc": {"y": 0, "x": 0}, "size": 20}, {"color": "#949fe3", "text": "ear", "initloc": {"y": 0, "x": 0}, "size": 20}, {"color": "#949fe3", "text": "lesson", "initloc": {"y": 0, "x": 0}, "size": 20}, {"color": "#949fe3", "text": "laughing", "initloc": {"y": 0, "x": 0}, "size": 20}, {"color": "#949fe3", "text": "lunch", "initloc": {"y": 0, "x": 0}, "size": 20}, {"color": "#949fe3", "text": "leggy", "initloc": {"y": 0, "x": 0}, "size": 20}, {"color": "#949fe3", "text": "skill", "initloc": {"y": 0, "x": 0}, "size": 20}, {"color": "#949fe3", "text": "unbelievable", "initloc": {"y": 0, "x": 0}, "size": 20}, {"color": "#949fe3", "text": "embarrassed", "initloc": {"y": 0, "x": 0}, "size": 20}, {"color": "#949fe3", "text": "laugh", "initloc": {"y": 0, "x": 0}, "size": 20}, {"color": "#949fe3", "text": "asshole", "initloc": {"y": 0, "x": 0}, "size": 20}, {"color": "#949fe3", "text": "cabbage", "initloc": {"y": 0, "x": 0}, "size": 20}, {"color": "#949fe3", "text": "say", "initloc": {"y": 0, "x": 0}, "size": 20}, {"color": "#949fe3", "text": "adults", "initloc": {"y": 0, "x": 0}, "size": 20}], "cluster": 0.0, "rgb": "#949fe3"}