{"p": 0.006, "barbin": 2, "score": 0.1425454601746358, "zyx": [17, 46, 71], "words": [{"color": "#949fe3", "text": "cabbage", "initloc": {"y": 0, "x": 0}, "size": 20}, {"color": "#949fe3", "text": "wash", "initloc": {"y": 0, "x": 0}, "size": 20}, {"color": "#949fe3", "text": "cloth", "initloc": {"y": 0, "x": 0}, "size": 20}, {"color": "#949fe3", "text": "chi", "initloc": {"y": 0, "x": 0}, "size": 20}, {"color": "#949fe3", "text": "sluttiest", "initloc": {"y": 0, "x": 0}, "size": 20}, {"color": "#949fe3", "text": "eyed", "initloc": {"y": 0, "x": 0}, "size": 20}, {"color": "#949fe3", "text": "sugar", "initloc": {"y": 0, "x": 0}, "size": 20}, {"color": "#949fe3", "text": "inhabit", "initloc": {"y": 0, "x": 0}, "size": 20}, {"color": "#949fe3", "text": "meaning", "initloc": {"y": 0, "x": 0}, "size": 20}, {"color": "#949fe3", "text": "stripper", "initloc": {"y": 0, "x": 0}, "size": 20}, {"color": "#949fe3", "text": "nuts", "initloc": {"y": 0, "x": 0}, "size": 20}, {"color": "#949fe3", "text": "bitch", "initloc": {"y": 0, "x": 0}, "size": 20}, {"color": "#949fe3", "text": "beans", "initloc": {"y": 0, "x": 0}, "size": 20}, {"color": "#949fe3", "text": "black", "initloc": {"y": 0, "x": 0}, "size": 20}, {"color": "#949fe3", "text": "jig", "initloc": {"y": 0, "x": 0}, "size": 20}, {"color": "#949fe3", "text": "wa", "initloc": {"y": 0, "x": 0}, "size": 20}, {"color": "#949fe3", "text": "squared", "initloc": {"y": 0, "x": 0}, "size": 20}, {"color": "#949fe3", "text": "optimized", "initloc": {"y": 0, "x": 0}, "size": 20}, {"color": "#949fe3", "text": "lower", "initloc": {"y": 0, "x": 0}, "size": 20}, {"color": "#949fe3", "text": "shit", "initloc": {"y": 0, "x": 0}, "size": 20}], "cluster": 0.0, "rgb": "#949fe3"}