{"p": 0.004, "barbin": 2, "score": 0.12217730462369235, "zyx": [20, 43, 32], "words": [{"color": "#949fe3", "text": "easy", "initloc": {"y": 0, "x": 0}, "size": 20}, {"color": "#949fe3", "text": "grad", "initloc": {"y": 0, "x": 0}, "size": 20}, {"color": "#949fe3", "text": "oh", "initloc": {"y": 0, "x": 0}, "size": 20}, {"color": "#949fe3", "text": "ang", "initloc": {"y": 0, "x": 0}, "size": 20}, {"color": "#949fe3", "text": "chi", "initloc": {"y": 0, "x": 0}, "size": 20}, {"color": "#949fe3", "text": "uh", "initloc": {"y": 0, "x": 0}, "size": 20}, {"color": "#949fe3", "text": "must", "initloc": {"y": 0, "x": 0}, "size": 20}, {"color": "#949fe3", "text": "sit", "initloc": {"y": 0, "x": 0}, "size": 20}, {"color": "#949fe3", "text": "easier", "initloc": {"y": 0, "x": 0}, "size": 20}, {"color": "#949fe3", "text": "you", "initloc": {"y": 0, "x": 0}, "size": 20}, {"color": "#949fe3", "text": "sta", "initloc": {"y": 0, "x": 0}, "size": 20}, {"color": "#949fe3", "text": "least", "initloc": {"y": 0, "x": 0}, "size": 20}, {"color": "#949fe3", "text": "bare", "initloc": {"y": 0, "x": 0}, "size": 20}, {"color": "#949fe3", "text": "wiser", "initloc": {"y": 0, "x": 0}, "size": 20}, {"color": "#949fe3", "text": "cute", "initloc": {"y": 0, "x": 0}, "size": 20}, {"color": "#949fe3", "text": "answer", "initloc": {"y": 0, "x": 0}, "size": 20}, {"color": "#949fe3", "text": "want", "initloc": {"y": 0, "x": 0}, "size": 20}, {"color": "#949fe3", "text": "either", "initloc": {"y": 0, "x": 0}, "size": 20}, {"color": "#949fe3", "text": "need", "initloc": {"y": 0, "x": 0}, "size": 20}, {"color": "#949fe3", "text": "stih", "initloc": {"y": 0, "x": 0}, "size": 20}], "cluster": 0.0, "rgb": "#949fe3"}