{"p": 0.25, "barbin": 0, "score": 0.00046028445147591816, "zyx": [19, 77, 43], "words": [{"color": "#F2EC14", "text": "laughing", "initloc": {"y": 0, "x": 0}, "size": 20}, {"color": "#F2EC14", "text": "shit", "initloc": {"y": 0, "x": 0}, "size": 20}, {"color": "#F2EC14", "text": "asshole", "initloc": {"y": 0, "x": 0}, "size": 20}, {"color": "#F2EC14", "text": "liar", "initloc": {"y": 0, "x": 0}, "size": 20}, {"color": "#F2EC14", "text": "exaggerated", "initloc": {"y": 0, "x": 0}, "size": 20}, {"color": "#F2EC14", "text": "knows", "initloc": {"y": 0, "x": 0}, "size": 20}, {"color": "#F2EC14", "text": "hey", "initloc": {"y": 0, "x": 0}, "size": 20}, {"color": "#F2EC14", "text": "yeah", "initloc": {"y": 0, "x": 0}, "size": 20}, {"color": "#F2EC14", "text": "doubt", "initloc": {"y": 0, "x": 0}, "size": 20}, {"color": "#F2EC14", "text": "alright", "initloc": {"y": 0, "x": 0}, "size": 20}, {"color": "#F2EC14", "text": "gonna", "initloc": {"y": 0, "x": 0}, "size": 20}, {"color": "#F2EC14", "text": "ours", "initloc": {"y": 0, "x": 0}, "size": 20}, {"color": "#F2EC14", "text": "unbelievable", "initloc": {"y": 0, "x": 0}, "size": 20}, {"color": "#F2EC14", "text": "everybody", "initloc": {"y": 0, "x": 0}, "size": 20}, {"color": "#F2EC14", "text": "eyes", "initloc": {"y": 0, "x": 0}, "size": 20}, {"color": "#F2EC14", "text": "scared", "initloc": {"y": 0, "x": 0}, "size": 20}, {"color": "#F2EC14", "text": "maybe", "initloc": {"y": 0, "x": 0}, "size": 20}, {"color": "#F2EC14", "text": "thing", "initloc": {"y": 0, "x": 0}, "size": 20}, {"color": "#F2EC14", "text": "fuck", "initloc": {"y": 0, "x": 0}, "size": 20}, {"color": "#F2EC14", "text": "talked", "initloc": {"y": 0, "x": 0}, "size": 20}], "cluster": 3.0, "rgb": "#F2EC14"}