{"p": 0.272, "barbin": 0, "score": 0.024449759570471706, "zyx": [13, 60, 18], "words": [{"color": "#EF2624", "text": "just", "initloc": {"y": 0, "x": 0}, "size": 20}, {"color": "#EF2624", "text": "glanced", "initloc": {"y": 0, "x": 0}, "size": 20}, {"color": "#EF2624", "text": "ones", "initloc": {"y": 0, "x": 0}, "size": 20}, {"color": "#EF2624", "text": "going", "initloc": {"y": 0, "x": 0}, "size": 20}, {"color": "#EF2624", "text": "me", "initloc": {"y": 0, "x": 0}, "size": 20}, {"color": "#EF2624", "text": "eyes", "initloc": {"y": 0, "x": 0}, "size": 20}, {"color": "#EF2624", "text": "walking", "initloc": {"y": 0, "x": 0}, "size": 20}, {"color": "#EF2624", "text": "walk", "initloc": {"y": 0, "x": 0}, "size": 20}, {"color": "#EF2624", "text": "pile", "initloc": {"y": 0, "x": 0}, "size": 20}, {"color": "#EF2624", "text": "looking", "initloc": {"y": 0, "x": 0}, "size": 20}, {"color": "#EF2624", "text": "course", "initloc": {"y": 0, "x": 0}, "size": 20}, {"color": "#EF2624", "text": "stuff", "initloc": {"y": 0, "x": 0}, "size": 20}, {"color": "#EF2624", "text": "straight", "initloc": {"y": 0, "x": 0}, "size": 20}, {"color": "#EF2624", "text": "look", "initloc": {"y": 0, "x": 0}, "size": 20}, {"color": "#EF2624", "text": "like", "initloc": {"y": 0, "x": 0}, "size": 20}, {"color": "#EF2624", "text": "foot", "initloc": {"y": 0, "x": 0}, "size": 20}, {"color": "#EF2624", "text": "side", "initloc": {"y": 0, "x": 0}, "size": 20}, {"color": "#EF2624", "text": "kinda", "initloc": {"y": 0, "x": 0}, "size": 20}, {"color": "#EF2624", "text": "way", "initloc": {"y": 0, "x": 0}, "size": 20}, {"color": "#EF2624", "text": "face", "initloc": {"y": 0, "x": 0}, "size": 20}], "cluster": 1.0, "rgb": "#EF2624"}